krish_ml/__init__.py
krish_ml/main.py
krish_ml-1.0.1.dist-info/METADATA
krish_ml-1.0.1.dist-info/WHEEL
krish_ml-1.0.1.dist-info/entry_points.txt
krish_ml-1.0.1.dist-info/top_level.txt
krish_ml-1.0.1.dist-info/RECORD
