Metadata-Version: 2.1
Name: krish_ml
Version: 1.0.1
Requires-Python: >=3.6
Requires-Dist: numpy
Requires-Dist: matplotlib
